{"skeleton":{"hash":"Show23cyMe7plwNyNMxGOM/OfTM","spine":"3.8.99","x":-539.45,"y":-304.73,"width":1162.83,"height":1203.89,"images":"./images/","audio":""},"bones":[{"name":"head_water_1","scaleX":1.009,"scaleY":1.009},{"name":"head_water_2","parent":"head_water_1","length":774.06,"rotation":-0.23,"x":2.21,"y":0.67},{"name":"fog","parent":"head_water_2","length":390.7,"rotation":88.43,"x":22.31,"y":290.2},{"name":"fog2","parent":"head_water_2","length":390.7,"rotation":88.43,"x":22.32,"y":288.44},{"name":"fog3","parent":"head_water_2","length":390.7,"rotation":88.43,"x":22.32,"y":288.84},{"name":"fog4","parent":"head_water_2","length":390.7,"rotation":88.43,"x":22.32,"y":288.64},{"name":"fog5","parent":"head_water_2","length":390.7,"rotation":88.43,"x":22.32,"y":288.47},{"name":"fog6","parent":"head_water_2","length":390.7,"rotation":88.43,"x":22.32,"y":288.39},{"name":"fog7","parent":"head_water_2","length":390.7,"rotation":88.43,"x":22.31,"y":289.31},{"name":"fog8","parent":"head_water_2","length":390.7,"rotation":88.43,"x":22.32,"y":287.92},{"name":"fog9","parent":"head_water_2","length":390.7,"rotation":88.43,"x":22.31,"y":289.2},{"name":"fog10","parent":"head_water_2","length":390.7,"rotation":88.43,"x":22.32,"y":288.48},{"name":"fog11","parent":"head_water_2","length":390.7,"rotation":88.43,"x":22.32,"y":288.45}],"slots":[{"name":"fog","bone":"fog","attachment":"glow"},{"name":"fog2","bone":"fog2","attachment":"glow"},{"name":"fog3","bone":"fog3","attachment":"glow"},{"name":"fog4","bone":"fog4","attachment":"glow"},{"name":"fog5","bone":"fog5","attachment":"glow"},{"name":"fog6","bone":"fog6","attachment":"glow"},{"name":"fog7","bone":"fog7","attachment":"glow"},{"name":"fog8","bone":"fog8","attachment":"glow"},{"name":"fog9","bone":"fog9","attachment":"glow"},{"name":"fog10","bone":"fog10","attachment":"glow"},{"name":"fog11","bone":"fog11","attachment":"glow"}],"skins":[{"name":"default","attachments":{"fog":{"glow":{"x":5.42,"y":-15.76,"scaleX":3.8414,"scaleY":3.8414,"rotation":-88.2,"width":300,"height":310}},"fog2":{"glow":{"x":5.42,"y":-15.76,"scaleX":3.8414,"scaleY":3.8414,"rotation":-88.2,"width":300,"height":310}},"fog3":{"glow":{"x":5.42,"y":-15.76,"scaleX":3.8414,"scaleY":3.8414,"rotation":-88.2,"width":300,"height":310}},"fog4":{"glow":{"x":5.42,"y":-15.76,"scaleX":3.8414,"scaleY":3.8414,"rotation":-88.2,"width":300,"height":310}},"fog5":{"glow":{"x":5.42,"y":-15.76,"scaleX":3.8414,"scaleY":3.8414,"rotation":-88.2,"width":300,"height":310}},"fog6":{"glow":{"x":5.42,"y":-15.76,"scaleX":3.8414,"scaleY":3.8414,"rotation":-88.2,"width":300,"height":310}},"fog7":{"glow":{"x":5.42,"y":-15.76,"scaleX":3.8414,"scaleY":3.8414,"rotation":-88.2,"width":300,"height":310}},"fog8":{"glow":{"x":5.42,"y":-15.76,"scaleX":3.8414,"scaleY":3.8414,"rotation":-88.2,"width":300,"height":310}},"fog9":{"glow":{"x":5.42,"y":-15.76,"scaleX":3.8414,"scaleY":3.8414,"rotation":-88.2,"width":300,"height":310}},"fog10":{"glow":{"x":5.42,"y":-15.76,"scaleX":3.8414,"scaleY":3.8414,"rotation":-88.2,"width":300,"height":310}},"fog11":{"glow":{"x":5.42,"y":-15.76,"scaleX":3.8414,"scaleY":3.8414,"rotation":-88.2,"width":300,"height":310}}}}],"animations":{"head_water_1":{"slots":{"fog":{"color":[{"time":0.4,"color":"ffffffff"},{"time":0.6333,"color":"ffffff00"}]},"fog2":{"color":[{"time":0.5333,"color":"ffffffff"},{"time":0.7667,"color":"ffffff00"}]},"fog3":{"color":[{"time":0.6667,"color":"ffffffff"},{"time":0.9,"color":"ffffff00"}]},"fog4":{"color":[{"time":1.1333,"color":"ffffffff"},{"time":1.4667,"color":"ffffff00"}]},"fog5":{"color":[{"time":1.2,"color":"ffffffff"},{"time":1.5333,"color":"ffffff00"}]},"fog6":{"color":[{"time":1.1667,"color":"ffffffff"},{"time":1.5,"color":"ffffff00"}]},"fog7":{"color":[{"time":0.6333,"color":"ffffffff"},{"time":0.8667,"color":"ffffff00"}]},"fog8":{"color":[{"time":0.7333,"color":"ffffffff"},{"time":1,"color":"ffffff00"}]},"fog9":{"color":[{"time":0.8333,"color":"ffffffff"},{"time":1.1333,"color":"ffffff00"}]},"fog10":{"color":[{"time":0.9667,"color":"ffffffff"},{"time":1.3,"color":"ffffff00"}]},"fog11":{"color":[{"time":0.9667,"color":"ffffffff"},{"time":1.3,"color":"ffffff00"}]}},"bones":{"fog":{"translate":[{},{"time":0.3,"x":1385.22},{"time":0.5667,"x":1607.68}],"scale":[{"x":0,"y":0},{"time":0.3},{"time":0.6,"x":1.836,"y":1.836}]},"fog2":{"translate":[{"time":0.1333},{"time":0.4333,"x":1385.22},{"time":0.7,"x":1607.68}],"scale":[{"x":0,"y":0,"curve":"stepped"},{"time":0.1333,"x":0,"y":0},{"time":0.4333},{"time":0.7333,"x":1.836,"y":1.836}]},"fog3":{"translate":[{"time":0.2333},{"time":0.5333,"x":1385.22},{"time":0.8333,"x":1607.68}],"scale":[{"x":0,"y":0,"curve":"stepped"},{"time":0.2333,"x":0,"y":0},{"time":0.5333},{"time":0.8667,"x":1.836,"y":1.836}]},"fog4":{"translate":[{"time":0.6333},{"time":0.9667,"x":1385.22},{"time":1.4,"x":1607.68}],"scale":[{"x":0,"y":0,"curve":"stepped"},{"time":0.6333,"x":0,"y":0},{"time":0.9667},{"time":1.4333,"x":1.836,"y":1.836}]},"fog5":{"translate":[{"time":0.6667},{"time":1.0333,"x":1385.22},{"time":1.4667,"x":1607.68}],"scale":[{"x":0,"y":0,"curve":"stepped"},{"time":0.6667,"x":0,"y":0},{"time":1.0333},{"time":1.5,"x":1.836,"y":1.836}]},"fog6":{"translate":[{"time":0.6333},{"time":1,"x":1385.22},{"time":1.4333,"x":1607.68}],"scale":[{"x":0,"y":0,"curve":"stepped"},{"time":0.6333,"x":0,"y":0},{"time":1},{"time":1.4667,"x":1.836,"y":1.836}]},"fog7":{"translate":[{"time":0.2},{"time":0.5,"x":1385.22},{"time":0.8,"x":1607.68}],"scale":[{"x":0,"y":0,"curve":"stepped"},{"time":0.2,"x":0,"y":0},{"time":0.5},{"time":0.8333,"x":1.836,"y":1.836}]},"fog8":{"translate":[{"time":0.3},{"time":0.6333,"x":1385.22},{"time":0.9333,"x":1607.68}],"scale":[{"x":0,"y":0,"curve":"stepped"},{"time":0.3,"x":0,"y":0},{"time":0.6333},{"time":0.9667,"x":1.836,"y":1.836}]},"fog9":{"translate":[{"time":0.3667},{"time":0.7,"x":1385.22},{"time":1.0667,"x":1607.68}],"scale":[{"x":0,"y":0,"curve":"stepped"},{"time":0.3667,"x":0,"y":0},{"time":0.7},{"time":1.1,"x":1.836,"y":1.836}]},"fog10":{"translate":[{"time":0.4667},{"time":0.8333,"x":1385.22},{"time":1.2333,"x":1607.68}],"scale":[{"x":0,"y":0,"curve":"stepped"},{"time":0.4667,"x":0,"y":0},{"time":0.8333},{"time":1.2667,"x":1.836,"y":1.836}]},"fog11":{"translate":[{"time":0.4667},{"time":0.8333,"x":1385.22},{"time":1.2333,"x":1607.68}],"scale":[{"x":0,"y":0,"curve":"stepped"},{"time":0.4667,"x":0,"y":0},{"time":0.8333},{"time":1.2667,"x":1.836,"y":1.836}]},"head_water_2":{"translate":[{},{"time":0.4333,"x":-1478.74}]}}}}}